arduino_rpc/__init__.py
arduino_rpc/code_gen.py
arduino_rpc/cpp_class_gen.py
arduino_rpc/dtypes.py
arduino_rpc/pavement_base.py
arduino_rpc/protobuf.py
arduino_rpc/proxy.py
arduino_rpc/rpc_data_frame.py
arduino_rpc/upload.py
arduino_rpc/.ropeproject/config.py
arduino_rpc/.ropeproject/globalnames
arduino_rpc/.ropeproject/history
arduino_rpc/.ropeproject/objectdb
arduino_rpc/Arduino/arduino_rpc/Array.h
arduino_rpc/Arduino/arduino_rpc/RPCBuffer.ht
arduino_rpc/Arduino/library/ArduinoRPC.h
arduino_rpc/Arduino/library/ArduinoRpc.zip
arduino_rpc/Arduino/library/Array.h
arduino_rpc/Arduino/library/ArraySerialization.h
arduino_rpc/Arduino/library/CommandPacketHandler.h
arduino_rpc/Arduino/library/I2CHandler.cpp
arduino_rpc/Arduino/library/I2CHandler.h
arduino_rpc/Arduino/library/RPCBuffer.c
arduino_rpc/Arduino/library/library.properties.t
arduino_rpc/Arduino/library/remote_i2c_command.h
arduino_rpc/Arduino/library/ArduinoRpc/library.properties
arduino_rpc/Arduino/library/ArduinoRpc/src/ArduinoRpc.h
arduino_rpc/Arduino/library/ArduinoRpc/src/ArduinoRpc/CommandPacketHandler.h
arduino_rpc/bin/__init__.py
arduino_rpc/bin/code_gen.py
arduino_rpc-1.7.post23.dist-info/DESCRIPTION.rst
arduino_rpc-1.7.post23.dist-info/METADATA
arduino_rpc-1.7.post23.dist-info/RECORD
arduino_rpc-1.7.post23.dist-info/WHEEL
arduino_rpc-1.7.post23.dist-info/metadata.json
arduino_rpc-1.7.post23.dist-info/pbr.json
arduino_rpc-1.7.post23.dist-info/top_level.txt
