Metadata-Version: 2.0
Name: arduino-rpc
Version: 1.7.post23
Summary: Code generation for memory-efficient remote-procedure-calls between a host CPU (Python) and a device (C++) (e.g., Arduino).
Home-page: http://github.com/wheeler-microfluidics/arduino_rpc.git
Author: Christian Fobel
Author-email: christian@fobel.net
License: GPLv2
Platform: UNKNOWN
Requires-Dist: arduino-helpers (>=0.3.post18)
Requires-Dist: arduino-memory (>=0.1.post3)
Requires-Dist: c-array-defs (>=0.2)
Requires-Dist: clang-helpers (>=0.3)
Requires-Dist: jinja2
Requires-Dist: nadamq (>=0.8.post1)
Requires-Dist: nanopb-helpers (>=0.4.post1)
Requires-Dist: pandas (>=0.15)
Requires-Dist: path-helpers (>=0.2)
Requires-Dist: serial-device (>=0.2)
